django_deprecation/__init__.py
django_deprecation/deprecated_field.py
django_deprecation-0.1.1.dist-info/METADATA
django_deprecation-0.1.1.dist-info/RECORD
django_deprecation-0.1.1.dist-info/WHEEL
django_deprecation-0.1.1.dist-info/top_level.txt
